<bill session="111" type="s" number="1082" updated="2023-01-11T13:19:01Z">
  <state datetime="2009-05-20">REFERRED</state>
  <status>
    <introduced datetime="2009-05-20"/>
  </status>
  <introduced datetime="2009-05-20"/>
  <titles>
    <title type="display">Generate Retirement Ownership Through Long-Term Holding Act of 2009</title>
    <title type="official" as="introduced">A bill to amend the Internal Revenue Code of 1986 to allow individuals to defer recognition of reinvested capital gains distributions from regulated investment companies.</title>
    <title type="short" as="introduced">Generate Retirement Ownership Through Long-Term Holding Act of 2009</title>
  </titles>
  <sponsor bioguide_id="C000880"/>
  <cosponsors>
    <cosponsor bioguide_id="J000177" joined="2009-05-20"/>
  </cosponsors>
  <actions>
    <action datetime="2009-05-20">
      <text>Introduced in Senate</text>
    </action>
    <action datetime="2009-05-20" state="REFERRED">
      <text>Read twice and referred to the Committee on Finance.</text>
    </action>
  </actions>
  <committees>
    <committee code="SSFI" name="Senate Finance" subcommittee="" activity="Referral"/>
  </committees>
  <relatedbills>
    <bill session="111" type="h" number="3429" relation="unknown"/>
  </relatedbills>
  <subjects>
    <term name="Taxation"/>
    <term name="Capital gains tax"/>
    <term name="Financial services and investments"/>
    <term name="Income tax exclusion"/>
    <term name="Interest, dividends, interest rates"/>
    <term name="Securities"/>
  </subjects>
  <amendments/>
  <summary date="2009-06-19T19:50:11Z" status="Introduced in Senate">Generate Retirement Ownership Through Long-Term Holding Act of 2009 - Amends the Internal Revenue Code to provide that no gain shall be recognized on the receipt of a capital gain dividend distributed by a regulated investment company if such dividend is automatically reinvested in additional shares of the company pursuant to a dividend reinvestment plan.</summary>
</bill>
