{
  "actions": [
    {
      "acted_at": "2005-09-13",
      "action_code": "Intro-H",
      "references": [],
      "text": "Introduced in House",
      "type": "action"
    },
    {
      "acted_at": "2005-09-13",
      "action_code": "H11100",
      "committees": [
        "HSWM"
      ],
      "references": [],
      "status": "REFERRED",
      "text": "Referred to the House Committee on Ways and Means.",
      "type": "referral"
    }
  ],
  "amendments": [],
  "bill_id": "hr3744-109",
  "bill_type": "hr",
  "by_request": false,
  "committee_reports": [],
  "committees": [
    {
      "activity": [
        "referral"
      ],
      "committee": "House Ways and Means",
      "committee_id": "HSWM"
    }
  ],
  "congress": "109",
  "cosponsors": [
    {
      "bioguide_id": "R000170",
      "district": "16",
      "name": "Reyes, Silvestre",
      "original_cosponsor": true,
      "sponsored_at": "2005-09-13",
      "state": "TX",
      "title": "Rep.",
      "withdrawn_at": null
    }
  ],
  "enacted_as": null,
  "history": {
    "active": false,
    "awaiting_signature": false,
    "enacted": false,
    "vetoed": false
  },
  "introduced_at": "2005-09-13",
  "number": "3744",
  "official_title": "To amend the Internal Revenue Code of 1986 to provide incentives for Americans to open their homes to fellow Americans from the Gulf Coast who were devastated by Hurricane Katrina, and for other purposes.",
  "popular_title": null,
  "related_bills": [],
  "short_title": "Katrina Aftermath Relief Effort Tax Credit Act",
  "sponsor": {
    "bioguide_id": "G000544",
    "district": "20",
    "name": "Gonzalez, Charles A.",
    "state": "TX",
    "title": "Rep.",
    "type": "person"
  },
  "status": "REFERRED",
  "status_at": "2005-09-13",
  "subjects": [
    "Agriculture and Food",
    "Alabama",
    "Clothing",
    "Costs",
    "Displaced persons",
    "Education",
    "Elementary and secondary education",
    "Elementary education",
    "Emergency Management",
    "Emergency housing",
    "Equipment and supplies",
    "Floods",
    "Higher education",
    "Housing and Community Development",
    "Hurricane aftermath legislation",
    "Hurricanes",
    "Income tax",
    "Louisiana",
    "Mississippi",
    "Secondary education",
    "Tax credits",
    "Tax returns",
    "Taxation",
    "Transportation and Public Works",
    "Travel costs",
    "Water Resources Development"
  ],
  "subjects_top_term": "Taxation",
  "summary": {
    "as": "Introduced in House",
    "asOf": "2005-09-13",
    "date": "2005-09-30T18:55:27Z",
    "text": "Katrina Aftermath Relief Effort Tax Credit Act - Amends the Internal Revenue Code to allow individual taxpayers a refundable tax credit for certain housing support expenses (e.g., food, clothing, and school supplies) paid or incurred between August 29, 2005, and December 31, 2006, to help individuals displaced by Hurricane Katrina. Limits the amount of such credit to $1,000 for any taxable year."
  },
  "titles": [
    {
      "as": null,
      "is_for_portion": false,
      "textVersionCode": null,
      "title": "Katrina Aftermath Relief Effort Tax Credit Act",
      "type": "display"
    },
    {
      "as": "introduced",
      "is_for_portion": false,
      "textVersionCode": null,
      "title": "To amend the Internal Revenue Code of 1986 to provide incentives for Americans to open their homes to fellow Americans from the Gulf Coast who were devastated by Hurricane Katrina, and for other purposes.",
      "type": "official"
    },
    {
      "as": "introduced",
      "is_for_portion": false,
      "textVersionCode": null,
      "title": "Katrina Aftermath Relief Effort Tax Credit Act",
      "type": "short"
    }
  ],
  "updated_at": "2023-01-13T04:50:13Z",
  "url": "https://www.govinfo.gov/bulkdata/BILLSTATUS/109/hr/BILLSTATUS-109hr3744.xml"
}