{
  "actions": [
    {
      "acted_at": "2011-05-23",
      "action_code": "Intro-H",
      "references": [],
      "text": "Introduced in House",
      "type": "action"
    },
    {
      "acted_at": "2011-05-23",
      "action_code": "H11100",
      "committees": [
        "HSED"
      ],
      "references": [],
      "status": "REFERRED",
      "text": "Referred to the House Committee on Education and the Workforce.",
      "type": "referral"
    },
    {
      "acted_at": "2011-09-08",
      "action_code": "",
      "committees": [
        "HSED"
      ],
      "references": [],
      "text": "Referred to the Subcommittee on Early Childhood, Elementary, and Secondary Education.",
      "type": "referral"
    }
  ],
  "amendments": [],
  "bill_id": "hr1951-112",
  "bill_type": "hr",
  "by_request": false,
  "committee_reports": [],
  "committees": [
    {
      "activity": [
        "referral"
      ],
      "committee": "House Education and the Workforce",
      "committee_id": "HSED"
    },
    {
      "activity": [
        "referral"
      ],
      "committee": "House Education and the Workforce",
      "committee_id": "HSED",
      "subcommittee": "Subcommittee on Early Childhood, Elementary, and Secondary Education",
      "subcommittee_id": "14"
    }
  ],
  "congress": "112",
  "cosponsors": [
    {
      "bioguide_id": "C001037",
      "district": "8",
      "name": "Capuano, Michael E.",
      "original_cosponsor": true,
      "sponsored_at": "2011-05-23",
      "state": "MA",
      "title": "Rep.",
      "withdrawn_at": null
    },
    {
      "bioguide_id": "C001078",
      "district": "11",
      "name": "Connolly, Gerald E.",
      "original_cosponsor": true,
      "sponsored_at": "2011-05-23",
      "state": "VA",
      "title": "Rep.",
      "withdrawn_at": null
    },
    {
      "bioguide_id": "F000455",
      "district": "11",
      "name": "Fudge, Marcia L.",
      "original_cosponsor": true,
      "sponsored_at": "2011-05-23",
      "state": "OH",
      "title": "Rep.",
      "withdrawn_at": null
    },
    {
      "bioguide_id": "H001046",
      "district": "1",
      "name": "Heinrich, Martin",
      "original_cosponsor": false,
      "sponsored_at": "2012-04-24",
      "state": "NM",
      "title": "Rep.",
      "withdrawn_at": null
    },
    {
      "bioguide_id": "H000627",
      "district": "22",
      "name": "Hinchey, Maurice D.",
      "original_cosponsor": true,
      "sponsored_at": "2011-05-23",
      "state": "NY",
      "title": "Rep.",
      "withdrawn_at": null
    },
    {
      "bioguide_id": "H001032",
      "district": "12",
      "name": "Holt, Rush",
      "original_cosponsor": false,
      "sponsored_at": "2011-11-02",
      "state": "NJ",
      "title": "Rep.",
      "withdrawn_at": null
    },
    {
      "bioguide_id": "J000126",
      "district": "30",
      "name": "Johnson, Eddie Bernice",
      "original_cosponsor": false,
      "sponsored_at": "2011-05-24",
      "state": "TX",
      "title": "Rep.",
      "withdrawn_at": null
    },
    {
      "bioguide_id": "K000172",
      "district": "5",
      "name": "Kildee, Dale E.",
      "original_cosponsor": false,
      "sponsored_at": "2011-06-16",
      "state": "MI",
      "title": "Rep.",
      "withdrawn_at": null
    },
    {
      "bioguide_id": "L000563",
      "district": "3",
      "name": "Lipinski, Daniel",
      "original_cosponsor": false,
      "sponsored_at": "2011-07-14",
      "state": "IL",
      "title": "Rep.",
      "withdrawn_at": null
    },
    {
      "bioguide_id": "L000565",
      "district": "2",
      "name": "Loebsack, David",
      "original_cosponsor": false,
      "sponsored_at": "2011-09-21",
      "state": "IA",
      "title": "Rep.",
      "withdrawn_at": null
    },
    {
      "bioguide_id": "M000087",
      "district": "14",
      "name": "Maloney, Carolyn B.",
      "original_cosponsor": false,
      "sponsored_at": "2011-07-28",
      "state": "NY",
      "title": "Rep.",
      "withdrawn_at": null
    },
    {
      "bioguide_id": "M001149",
      "district": "2",
      "name": "Michaud, Michael H.",
      "original_cosponsor": false,
      "sponsored_at": "2011-11-15",
      "state": "ME",
      "title": "Rep.",
      "withdrawn_at": null
    },
    {
      "bioguide_id": "P000523",
      "district": "4",
      "name": "Price, David E.",
      "original_cosponsor": false,
      "sponsored_at": "2011-07-13",
      "state": "NC",
      "title": "Rep.",
      "withdrawn_at": null
    },
    {
      "bioguide_id": "R000462",
      "district": "9",
      "name": "Rothman, Steven R.",
      "original_cosponsor": false,
      "sponsored_at": "2011-07-13",
      "state": "NJ",
      "title": "Rep.",
      "withdrawn_at": null
    },
    {
      "bioguide_id": "W000793",
      "district": "1",
      "name": "Wu, David",
      "original_cosponsor": true,
      "sponsored_at": "2011-05-23",
      "state": "OR",
      "title": "Rep.",
      "withdrawn_at": null
    }
  ],
  "enacted_as": null,
  "history": {
    "active": false,
    "awaiting_signature": false,
    "enacted": false,
    "vetoed": false
  },
  "introduced_at": "2011-05-23",
  "number": "1951",
  "official_title": "To award planning grants and implementation grants to State educational agencies to enable the State educational agencies to complete comprehensive planning to carry out activities designed to integrate engineering education into K-12 instruction and curriculum and to provide evaluation grants to measure efficacy of K-12 engineering education.",
  "popular_title": null,
  "related_bills": [
    {
      "bill_id": "s969-112",
      "identified_by": "CRS",
      "reason": "identical",
      "type": "bill"
    }
  ],
  "short_title": "E 2 for Innovation Act",
  "sponsor": {
    "bioguide_id": "T000469",
    "district": "21",
    "name": "Tonko, Paul",
    "state": "NY",
    "title": "Rep.",
    "type": "person"
  },
  "status": "REFERRED",
  "status_at": "2011-05-23",
  "subjects": [
    "Academic performance and assessments",
    "Education",
    "Education of the disadvantaged",
    "Education programs funding",
    "Educational technology and distance education",
    "Elementary and secondary education",
    "Government information and archives",
    "Science and engineering education",
    "Teaching, teachers, curricula"
  ],
  "subjects_top_term": "Education",
  "summary": {
    "as": "Introduced in House",
    "asOf": "2011-05-23",
    "date": "2011-06-01T15:27:45Z",
    "text": "Engineering Education for Innovation Act or E 2 for Innovation Act - Authorizes the Secretary of Education to award planning grants and matching implementation grants to states to integrate engineering education into kindergarten through grade 12 (K-12) instruction and curricula.\n\nRequires each state that desires an implementation grant to develop quantifiable benchmarks for activities supported by such grants and submit them to the Secretary for approval.\n\nRequires states to use implementation grants to: (1) establish assessment tools and challenging academic content and achievement standards for engineering education, (2) develop or obtain effective engineering education curricula, (3) develop or improve engineering teacher training programs, and (4) recruit qualified engineering teachers for needy schools.\n\nAuthorizes states to use such grants to: (1) facilitate distance learning and online education in engineering, and (2) invest in after-school engineering education programs.\n\nDirects the Institute of Education Sciences to support engineering education research and an evaluation of this Act's grant programs.\n\nRequires the Secretary to use the evaluation's findings to provide information to the public and technical assistance to states on best practices and promising innovations in K-12 engineering education."
  },
  "titles": [
    {
      "as": "introduced",
      "is_for_portion": false,
      "textVersionCode": null,
      "title": "E 2 for Innovation Act",
      "type": "short"
    },
    {
      "as": "introduced",
      "is_for_portion": false,
      "textVersionCode": null,
      "title": "Engineering Education for Innovation Act",
      "type": "short"
    },
    {
      "as": null,
      "is_for_portion": false,
      "textVersionCode": null,
      "title": "Engineering Education for Innovation Act",
      "type": "display"
    },
    {
      "as": "introduced",
      "is_for_portion": false,
      "textVersionCode": null,
      "title": "To award planning grants and implementation grants to State educational agencies to enable the State educational agencies to complete comprehensive planning to carry out activities designed to integrate engineering education into K-12 instruction and curriculum and to provide evaluation grants to measure efficacy of K-12 engineering education.",
      "type": "official"
    }
  ],
  "updated_at": "2019-11-15T21:05:17Z",
  "url": "https://www.govinfo.gov/bulkdata/BILLSTATUS/112/hr/BILLSTATUS-112hr1951.xml"
}