{
  "actions": [
    {
      "acted_at": "2025-04-01",
      "action_code": "H11100",
      "references": [],
      "text": "Submitted in House",
      "type": "action"
    },
    {
      "acted_at": "2025-04-01",
      "action_code": "H11100",
      "committees": [
        "HSED"
      ],
      "references": [],
      "status": "REFERRED",
      "text": "Referred to the House Committee on Education and Workforce.",
      "type": "referral"
    }
  ],
  "amendments": [],
  "bill_id": "hres284-119",
  "bill_type": "hres",
  "by_request": false,
  "committee_reports": [],
  "committees": [
    {
      "activity": [
        "Referred To"
      ],
      "committee": "House Education and Workforce",
      "committee_id": "HSED"
    }
  ],
  "congress": "119",
  "cosponsors": [
    {
      "bioguide_id": "G000583",
      "district": "5",
      "name": "Gottheimer, Josh",
      "original_cosponsor": false,
      "sponsored_at": "2025-05-07",
      "state": "NJ",
      "title": "Rep.",
      "withdrawn_at": null
    },
    {
      "bioguide_id": "L000599",
      "district": "17",
      "name": "Lawler, Michael",
      "original_cosponsor": false,
      "sponsored_at": "2025-04-02",
      "state": "NY",
      "title": "Rep.",
      "withdrawn_at": null
    },
    {
      "bioguide_id": "M001214",
      "district": "1",
      "name": "Mrvan, Frank J.",
      "original_cosponsor": true,
      "sponsored_at": "2025-04-01",
      "state": "IN",
      "title": "Rep.",
      "withdrawn_at": null
    },
    {
      "bioguide_id": "W000795",
      "district": "2",
      "name": "Wilson, Joe",
      "original_cosponsor": true,
      "sponsored_at": "2025-04-01",
      "state": "SC",
      "title": "Rep.",
      "withdrawn_at": null
    }
  ],
  "enacted_as": null,
  "history": {
    "active": false,
    "awaiting_signature": false,
    "enacted": false,
    "vetoed": false
  },
  "introduced_at": "2025-04-01",
  "number": "284",
  "official_title": "Expressing support for the goals and ideals of National Child Abuse Prevention Month.",
  "popular_title": null,
  "related_bills": [],
  "short_title": null,
  "sponsor": {
    "bioguide_id": "B001282",
    "district": "6",
    "name": "Barr, Andy",
    "state": "KY",
    "title": "Rep.",
    "type": "person"
  },
  "status": "REFERRED",
  "status_at": "2025-04-01",
  "subjects": [
    "Families"
  ],
  "subjects_top_term": "Families",
  "summary": null,
  "titles": [
    {
      "as": null,
      "is_for_portion": false,
      "textVersionCode": null,
      "title": "Expressing support for the goals and ideals of National Child Abuse Prevention Month.",
      "type": "display"
    },
    {
      "as": "introduced",
      "is_for_portion": false,
      "textVersionCode": null,
      "title": "Expressing support for the goals and ideals of National Child Abuse Prevention Month.",
      "type": "official"
    }
  ],
  "updated_at": "2025-07-21T19:44:15Z",
  "url": "https://www.govinfo.gov/bulkdata/BILLSTATUS/119/hres/BILLSTATUS-119hres284.xml"
}