<?xml version="1.0" encoding="utf-8" standalone="no"?>
<billStatus>
  <version>3.0.0</version>
  <bill>
    <number>500</number>
    <updateDate>2022-02-03T05:09:48Z</updateDate>
    <updateDateIncludingText>2022-02-03T05:09:48Z</updateDateIncludingText>
    <originChamber>Senate</originChamber>
    <originChamberCode>S</originChamberCode>
    <type>SRES</type>
    <introducedDate>2008-04-03</introducedDate>
    <congress>110</congress>
    <committees>
      <item>
        <systemCode>ssas00</systemCode>
        <name>Armed Services Committee</name>
        <chamber>Senate</chamber>
        <type>Standing</type>
        <activities>
          <item>
            <name>Referred to</name>
            <date>2008-04-03T17:01:29Z</date>
          </item>
        </activities>
      </item>
    </committees>
    <relatedBills>
      <item>
        <title>Honoring military children during "National Month of the Military Child".</title>
        <congress>110</congress>
        <number>265</number>
        <type>HRES</type>
        <latestAction>
          <actionDate>2008-04-08</actionDate>
          <text>Motion to reconsider laid on the table Agreed to without objection.</text>
          <actionTime>14:36:16</actionTime>
        </latestAction>
        <relationshipDetails>
          <item>
            <type>Related bill</type>
            <identifiedBy>CRS</identifiedBy>
          </item>
        </relationshipDetails>
      </item>
    </relatedBills>
    <actions>
      <item>
        <actionDate>2008-04-07</actionDate>
        <text>Sponsor introductory remarks on measure. (CR S2634-2635)</text>
        <type>IntroReferral</type>
        <actionCode>B00100</actionCode>
        <sourceSystem>
          <code>9</code>
          <name>Library of Congress</name>
        </sourceSystem>
      </item>
      <item>
        <actionDate>2008-04-03</actionDate>
        <committees>
          <item>
            <systemCode>ssas00</systemCode>
            <name>Armed Services Committee</name>
          </item>
        </committees>
        <sourceSystem>
          <name>Senate</name>
        </sourceSystem>
        <text>Referred to the Committee on Armed Services. (text of measure as introduced: CR S2450)</text>
        <type>IntroReferral</type>
      </item>
      <item>
        <actionDate>2008-04-03</actionDate>
        <text>Introduced in Senate</text>
        <type>IntroReferral</type>
        <actionCode>10000</actionCode>
        <sourceSystem>
          <code>9</code>
          <name>Library of Congress</name>
        </sourceSystem>
      </item>
    </actions>
    <sponsors>
      <item>
        <bioguideId>K000105</bioguideId>
        <fullName>Sen. Kennedy, Edward M. [D-MA]</fullName>
        <firstName>EDWARD</firstName>
        <lastName>KENNEDY</lastName>
        <party>D</party>
        <state>MA</state>
        <middleName>MOORE</middleName>
        <isByRequest>N</isByRequest>
      </item>
    </sponsors>
    <cosponsors>
      <item>
        <bioguideId>B001233</bioguideId>
        <fullName>Sen. Bayh, Evan [D-IN]</fullName>
        <firstName>EVAN</firstName>
        <lastName>BAYH</lastName>
        <party>D</party>
        <state>IN</state>
        <sponsorshipDate>2008-04-03</sponsorshipDate>
        <isOriginalCosponsor>True</isOriginalCosponsor>
      </item>
      <item>
        <bioguideId>W000802</bioguideId>
        <fullName>Sen. Whitehouse, Sheldon [D-RI]</fullName>
        <firstName>Sheldon</firstName>
        <lastName>Whitehouse</lastName>
        <party>D</party>
        <state>RI</state>
        <sponsorshipDate>2008-04-14</sponsorshipDate>
        <isOriginalCosponsor>False</isOriginalCosponsor>
      </item>
      <item>
        <bioguideId>B000944</bioguideId>
        <fullName>Sen. Brown, Sherrod [D-OH]</fullName>
        <firstName>Sherrod</firstName>
        <lastName>Brown</lastName>
        <party>D</party>
        <state>OH</state>
        <sponsorshipDate>2008-04-14</sponsorshipDate>
        <isOriginalCosponsor>False</isOriginalCosponsor>
      </item>
      <item>
        <bioguideId>M000702</bioguideId>
        <fullName>Sen. Mikulski, Barbara A. [D-MD]</fullName>
        <firstName>BARBARA</firstName>
        <lastName>MIKULSKI</lastName>
        <party>D</party>
        <state>MD</state>
        <middleName>ANN</middleName>
        <sponsorshipDate>2008-04-14</sponsorshipDate>
        <isOriginalCosponsor>False</isOriginalCosponsor>
      </item>
      <item>
        <bioguideId>M001170</bioguideId>
        <fullName>Sen. McCaskill, Claire [D-MO]</fullName>
        <firstName>Claire</firstName>
        <lastName>McCaskill</lastName>
        <party>D</party>
        <state>MO</state>
        <sponsorshipDate>2008-04-14</sponsorshipDate>
        <isOriginalCosponsor>False</isOriginalCosponsor>
      </item>
      <item>
        <bioguideId>L000261</bioguideId>
        <fullName>Sen. Levin, Carl [D-MI]</fullName>
        <firstName>CARL</firstName>
        <lastName>LEVIN</lastName>
        <party>D</party>
        <state>MI</state>
        <middleName>MILTON</middleName>
        <sponsorshipDate>2008-04-14</sponsorshipDate>
        <isOriginalCosponsor>False</isOriginalCosponsor>
      </item>
      <item>
        <bioguideId>L000550</bioguideId>
        <fullName>Sen. Landrieu, Mary L. [D-LA]</fullName>
        <firstName>MARY</firstName>
        <lastName>LANDRIEU</lastName>
        <party>D</party>
        <state>LA</state>
        <sponsorshipDate>2008-04-14</sponsorshipDate>
        <isOriginalCosponsor>False</isOriginalCosponsor>
      </item>
      <item>
        <bioguideId>C001041</bioguideId>
        <fullName>Sen. Clinton, Hillary Rodham [D-NY]</fullName>
        <firstName>HILLARY</firstName>
        <lastName>CLINTON</lastName>
        <party>D</party>
        <state>NY</state>
        <middleName>R</middleName>
        <sponsorshipDate>2008-04-14</sponsorshipDate>
        <isOriginalCosponsor>False</isOriginalCosponsor>
      </item>
      <item>
        <bioguideId>C001070</bioguideId>
        <fullName>Sen. Casey, Robert P., Jr. [D-PA]</fullName>
        <firstName>Bob</firstName>
        <lastName>Casey</lastName>
        <party>D</party>
        <state>PA</state>
        <sponsorshipDate>2008-04-14</sponsorshipDate>
        <isOriginalCosponsor>False</isOriginalCosponsor>
      </item>
      <item>
        <bioguideId>B000444</bioguideId>
        <fullName>Sen. Biden, Joseph R., Jr. [D-DE]</fullName>
        <firstName>JOSEPH</firstName>
        <lastName>BIDEN</lastName>
        <party>D</party>
        <state>DE</state>
        <middleName>ROBINETTE</middleName>
        <sponsorshipDate>2008-04-14</sponsorshipDate>
        <isOriginalCosponsor>False</isOriginalCosponsor>
      </item>
      <item>
        <bioguideId>O000167</bioguideId>
        <fullName>Sen. Obama, Barack [D-IL]</fullName>
        <firstName>Barack</firstName>
        <lastName>Obama</lastName>
        <party>D</party>
        <state>IL</state>
        <sponsorshipDate>2008-04-15</sponsorshipDate>
        <isOriginalCosponsor>False</isOriginalCosponsor>
      </item>
    </cosponsors>
    <policyArea>
      <name>Commemorations</name>
    </policyArea>
    <subjects>
      <legislativeSubjects>
        <item>
          <name>Armed Forces and National Security</name>
        </item>
        <item>
          <name>Associations, institutions, etc.</name>
        </item>
        <item>
          <name>Charities</name>
        </item>
        <item>
          <name>Congressional tributes</name>
        </item>
        <item>
          <name>Families</name>
        </item>
        <item>
          <name>Military dependents</name>
        </item>
        <item>
          <name>Social Welfare</name>
        </item>
        <item>
          <name>Special months</name>
        </item>
      </legislativeSubjects>
      <policyArea>
        <name>Commemorations</name>
      </policyArea>
    </subjects>
    <summaries>
      <summary>
        <versionCode>00</versionCode>
        <actionDate>2008-04-03</actionDate>
        <actionDesc>Introduced in Senate</actionDesc>
        <updateDate>2008-06-17T21:06:33Z</updateDate>
        <text><![CDATA[ <p>Joins the Secretary of Defense in honoring the children of members of the Armed Forces and recognizes that they share in the burden of protecting the nation.</p> <p>Urges the people of the United States to join the military community in observing April as National Month of the Military Child.</p> <p>Recognizes with great appreciation the contributions of private sector organizations in providing resources and assistance to military families and their communities.</p>]]></text>
      </summary>
    </summaries>
    <title>A resolution honoring military children during "National Month of the Military Child".</title>
    <titles>
      <item>
        <titleType>Display Title</titleType>
        <title>A resolution honoring military children during "National Month of the Military Child".</title>
      </item>
      <item>
        <titleType>Official Title as Introduced</titleType>
        <title>A resolution honoring military children during "National Month of the Military Child".</title>
      </item>
    </titles>
    <textVersions>
      <item>
        <type>Introduced in Senate</type>
        <date>2008-04-03T04:00:00Z</date>
        <formats>
          <item>
            <url>https://www.govinfo.gov/content/pkg/BILLS-110sres500is/xml/BILLS-110sres500is.xml</url>
          </item>
        </formats>
      </item>
    </textVersions>
    <latestAction>
      <actionDate>2008-04-07</actionDate>
      <text>Sponsor introductory remarks on measure. (CR S2634-2635)</text>
    </latestAction>
  </bill>
  <dublinCore xmlns:dc="http://purl.org/dc/elements/1.1/">
    <dc:format>text/xml</dc:format>
    <dc:language>EN</dc:language>
    <dc:rights>Pursuant to Title 17 Section 105 of the United States Code, this file is not subject to copyright protection and is in the public domain.</dc:rights>
    <dc:contributor>Congressional Research Service, Library of Congress</dc:contributor>
    <dc:description>This file contains bill summaries and statuses for federal legislation. A bill summary describes the most significant provisions of a piece of legislation and details the effects the legislative text may have on current law and federal programs. Bill summaries are authored by the Congressional Research Service (CRS) of the Library of Congress. As stated in Public Law 91-510 (2 USC 166 (d)(6)), one of the duties of CRS is "to prepare summaries and digests of bills and resolutions of a public general nature introduced in the Senate or House of Representatives". For more information, refer to the User Guide that accompanies this file.</dc:description>
  </dublinCore>
</billStatus>
