{
  "actions": [
    {
      "acted_at": "2005-01-25",
      "action_code": "10000",
      "references": [],
      "text": "Introduced in Senate",
      "type": "action"
    },
    {
      "acted_at": "2005-01-25",
      "action_code": "B00100",
      "references": [
        {
          "reference": "CR S492-493",
          "type": null
        }
      ],
      "text": "Sponsor introductory remarks on measure.",
      "type": "action"
    },
    {
      "acted_at": "2005-01-25",
      "action_code": "",
      "committees": [
        "SSEG"
      ],
      "references": [],
      "status": "REFERRED",
      "text": "Read twice and referred to the Committee on Energy and Natural Resources.",
      "type": "referral"
    },
    {
      "acted_at": "2005-04-25",
      "action_code": "",
      "references": [],
      "text": "Message on Senate action sent to the House.",
      "type": "action"
    }
  ],
  "amendments": [],
  "bill_id": "s164-109",
  "bill_type": "s",
  "by_request": false,
  "committee_reports": [],
  "committees": [
    {
      "activity": [
        "referral"
      ],
      "committee": "Senate Energy and Natural Resources",
      "committee_id": "SSEG"
    }
  ],
  "congress": "109",
  "cosponsors": [],
  "enacted_as": null,
  "history": {
    "active": true,
    "active_at": "2005-04-25",
    "awaiting_signature": false,
    "enacted": false,
    "vetoed": false
  },
  "introduced_at": "2005-01-25",
  "number": "164",
  "official_title": "A bill to provide for the acquisition of certain property in Washington County, Utah.",
  "popular_title": null,
  "related_bills": [],
  "short_title": null,
  "sponsor": {
    "bioguide_id": "B000382",
    "district": null,
    "name": "Bennett, Robert F.",
    "state": "UT",
    "title": "Sen.",
    "type": "person"
  },
  "status": "REFERRED",
  "status_at": "2005-01-25",
  "subjects": [
    "Compensation (Law)",
    "Eminent domain",
    "Land transfers",
    "Law",
    "Natural areas",
    "Public lands and natural resources",
    "Real estate development",
    "Utah"
  ],
  "subjects_top_term": "Public lands and natural resources",
  "summary": {
    "as": "Introduced in Senate",
    "asOf": "2005-01-25",
    "date": "2005-03-03T22:14:34Z",
    "text": "Provides for Federal acquisition of: (1) the fee simple interest in certain real property owned by Environmental Land Technology, Ltd. (ELT) and other parties, within the Red Cliffs Reserve in Washington County, Utah; and (2) the fee simple interest in certain real property owned by ELT, adjacent to the Red Cliffs Reserve. Directs the Secretary of the Interior to fairly compensate the owners of such lands."
  },
  "titles": [
    {
      "as": null,
      "is_for_portion": false,
      "textVersionCode": null,
      "title": "A bill to provide for the acquisition of certain property in Washington County, Utah.",
      "type": "display"
    },
    {
      "as": "introduced",
      "is_for_portion": false,
      "textVersionCode": null,
      "title": "A bill to provide for the acquisition of certain property in Washington County, Utah.",
      "type": "official"
    }
  ],
  "updated_at": "2022-02-03T05:25:25Z",
  "url": "https://www.govinfo.gov/bulkdata/BILLSTATUS/109/s/BILLSTATUS-109s164.xml"
}