{
  "actions": [
    {
      "acted_at": "2021-07-01",
      "action_code": "Intro-H",
      "references": [],
      "text": "Introduced in House",
      "type": "action"
    },
    {
      "acted_at": "2021-07-01",
      "action_code": "H11100",
      "committees": [
        "HSAS"
      ],
      "references": [],
      "status": "REFERRED",
      "text": "Referred to the House Committee on Armed Services.",
      "type": "referral"
    }
  ],
  "amendments": [],
  "bill_id": "hr4343-117",
  "bill_type": "hr",
  "by_request": false,
  "committee_reports": [],
  "committees": [
    {
      "activity": [
        "referral"
      ],
      "committee": "House Armed Services",
      "committee_id": "HSAS"
    }
  ],
  "congress": "117",
  "cosponsors": [
    {
      "bioguide_id": "P000613",
      "district": "20",
      "name": "Panetta, Jimmy",
      "original_cosponsor": true,
      "sponsored_at": "2021-07-01",
      "state": "CA",
      "title": "Rep.",
      "withdrawn_at": null
    }
  ],
  "enacted_as": null,
  "history": {
    "active": false,
    "awaiting_signature": false,
    "enacted": false,
    "vetoed": false
  },
  "introduced_at": "2021-07-01",
  "number": "4343",
  "official_title": "To amend title 10, United States Code, to authorize certain retired members of the Armed Forces to be placed in the Ready Reserve and to receive retired pay and the pay and allowances for duty that member performs.",
  "popular_title": null,
  "related_bills": [],
  "short_title": "Patriot Retention Act",
  "sponsor": {
    "bioguide_id": "W000815",
    "district": "2",
    "name": "Wenstrup, Brad R.",
    "state": "OH",
    "title": "Rep.",
    "type": "person"
  },
  "status": "REFERRED",
  "status_at": "2021-07-01",
  "subjects": [
    "Armed forces and national security"
  ],
  "subjects_top_term": "Armed forces and national security",
  "summary": {
    "as": "Introduced in House",
    "asOf": "2021-07-01",
    "date": "2022-09-23T13:48:49Z",
    "text": "Patriot Retention Act\n\nThis bill allows a retired service member who has more than 20 years of service, and who possesses a skill for which a critical shortage exists, to serve as a paid member of the Ready Reserve of the Armed Forces and concurrently receive retired pay."
  },
  "titles": [
    {
      "as": "introduced",
      "is_for_portion": false,
      "textVersionCode": null,
      "title": "To amend title 10, United States Code, to authorize certain retired members of the Armed Forces to be placed in the Ready Reserve and to receive retired pay and the pay and allowances for duty that member performs.",
      "type": "official"
    },
    {
      "as": null,
      "is_for_portion": false,
      "textVersionCode": null,
      "title": "Patriot Retention Act",
      "type": "display"
    },
    {
      "as": "introduced",
      "is_for_portion": false,
      "textVersionCode": null,
      "title": "Patriot Retention Act",
      "type": "short"
    }
  ],
  "updated_at": "2022-12-31T05:07:57Z",
  "url": "https://www.govinfo.gov/bulkdata/BILLSTATUS/117/hr/BILLSTATUS-117hr4343.xml"
}