{
  "actions": [
    {
      "acted_at": "2022-09-21",
      "action_code": "10000",
      "references": [],
      "text": "Introduced in Senate",
      "type": "action"
    },
    {
      "acted_at": "2022-09-21",
      "action_code": "",
      "committees": [
        "SSJU"
      ],
      "references": [],
      "status": "REFERRED",
      "text": "Read twice and referred to the Committee on the Judiciary.",
      "type": "referral"
    }
  ],
  "amendments": [],
  "bill_id": "s4916-117",
  "bill_type": "s",
  "by_request": false,
  "committee_reports": [],
  "committees": [
    {
      "activity": [
        "referral"
      ],
      "committee": "Senate Judiciary",
      "committee_id": "SSJU"
    }
  ],
  "congress": "117",
  "cosponsors": [
    {
      "bioguide_id": "B001288",
      "district": null,
      "name": "Booker, Cory A.",
      "original_cosponsor": false,
      "sponsored_at": "2022-11-14",
      "state": "NJ",
      "title": "Sen.",
      "withdrawn_at": null
    },
    {
      "bioguide_id": "C001035",
      "district": null,
      "name": "Collins, Susan M.",
      "original_cosponsor": false,
      "sponsored_at": "2022-09-22",
      "state": "ME",
      "title": "Sen.",
      "withdrawn_at": null
    },
    {
      "bioguide_id": "D000622",
      "district": null,
      "name": "Duckworth, Tammy",
      "original_cosponsor": false,
      "sponsored_at": "2022-11-15",
      "state": "IL",
      "title": "Sen.",
      "withdrawn_at": null
    },
    {
      "bioguide_id": "D000563",
      "district": null,
      "name": "Durbin, Richard J.",
      "original_cosponsor": false,
      "sponsored_at": "2022-11-14",
      "state": "IL",
      "title": "Sen.",
      "withdrawn_at": null
    },
    {
      "bioguide_id": "M001153",
      "district": null,
      "name": "Murkowski, Lisa",
      "original_cosponsor": false,
      "sponsored_at": "2022-10-11",
      "state": "AK",
      "title": "Sen.",
      "withdrawn_at": null
    },
    {
      "bioguide_id": "S001198",
      "district": null,
      "name": "Sullivan, Dan",
      "original_cosponsor": false,
      "sponsored_at": "2022-11-14",
      "state": "AK",
      "title": "Sen.",
      "withdrawn_at": null
    }
  ],
  "enacted_as": null,
  "history": {
    "active": false,
    "awaiting_signature": false,
    "enacted": false,
    "vetoed": false
  },
  "introduced_at": "2022-09-21",
  "number": "4916",
  "official_title": "A bill to reauthorize the Runaway and Homeless Youth Act, and for other purposes.",
  "popular_title": null,
  "related_bills": [
    {
      "bill_id": "hr8948-117",
      "identified_by": "CRS",
      "reason": "identical",
      "type": "bill"
    }
  ],
  "short_title": "Runaway and Homeless Youth and Trafficking Prevention Act of 2022",
  "sponsor": {
    "bioguide_id": "L000174",
    "district": null,
    "name": "Leahy, Patrick J.",
    "state": "VT",
    "title": "Sen.",
    "type": "person"
  },
  "status": "REFERRED",
  "status_at": "2022-09-21",
  "subjects": [
    "Families"
  ],
  "subjects_top_term": "Families",
  "summary": {
    "as": "Introduced in Senate",
    "asOf": "2022-09-21",
    "date": "2023-07-31T16:28:52Z",
    "text": "Runaway and Homeless Youth and Trafficking Prevention Act of 2022\n\nThis bill reauthorizes through FY2027 and expands programs for runaway, homeless, and disconnected youth, including resources and services to support youth victims of human trafficking and youth at risk of being trafficked."
  },
  "titles": [
    {
      "as": null,
      "is_for_portion": false,
      "textVersionCode": null,
      "title": "Runaway and Homeless Youth and Trafficking Prevention Act of 2022",
      "type": "display"
    },
    {
      "as": "introduced",
      "is_for_portion": false,
      "textVersionCode": null,
      "title": "Runaway and Homeless Youth and Trafficking Prevention Act of 2022",
      "type": "short"
    },
    {
      "as": "introduced",
      "is_for_portion": false,
      "textVersionCode": null,
      "title": "A bill to reauthorize the Runaway and Homeless Youth Act, and for other purposes.",
      "type": "official"
    }
  ],
  "updated_at": "2023-07-31T16:30:25Z",
  "url": "https://www.govinfo.gov/bulkdata/BILLSTATUS/117/s/BILLSTATUS-117s4916.xml"
}