{
  "actions": [
    {
      "acted_at": "2004-05-11",
      "action_code": "",
      "how": "roll",
      "references": [],
      "result": "fail",
      "roll": 90,
      "text": "Amendment SA 3134 not agreed to in Senate by Yea-Nay Vote. 23 - 74. Record Vote Number: 90.",
      "type": "vote",
      "vote_type": "vote",
      "where": "s"
    },
    {
      "acted_at": "2004-05-11",
      "action_code": "",
      "references": [],
      "text": "Amendment SA 3134 proposed by Senator Hollings. (consideration: CR S5194-5199) To strike the international tax provisions that are unrelated to the FSC/ETI repeal and eliminate the phase-in of the deduction for qualified production activities income.",
      "type": "action"
    },
    {
      "acted_at": "2004-05-11",
      "action_code": "95000",
      "references": [],
      "text": "Senate amendment not agreed to: Amendment SA 3134 not agreed to in Senate by Yea-Nay Vote. 23 - 74. Record Vote Number: 90.",
      "type": "action"
    },
    {
      "acted_at": "2004-05-11",
      "action_code": "97000",
      "references": [],
      "text": "Roll call votes on amendments in Senate: Amendment SA 3134 not agreed to in Senate by Yea-Nay Vote. 23 - 74. Record Vote Number: 90.",
      "type": "action"
    },
    {
      "acted_at": "2004-05-11",
      "action_code": "93000",
      "references": [
        {
          "reference": "CR S5194-5199",
          "type": "consideration"
        }
      ],
      "text": "Senate amendment proposed (on the floor): Amendment SA 3134 proposed by Senator Hollings.",
      "type": "action"
    },
    {
      "acted_at": "2004-05-10",
      "action_code": "91000",
      "references": [],
      "text": "Senate amendment submitted",
      "type": "action"
    }
  ],
  "amendment_id": "samdt3134-108",
  "amendment_type": "samdt",
  "amends_amendment": null,
  "amends_bill": {
    "bill_id": "s1637-108",
    "bill_type": "s",
    "congress": 108,
    "number": 1637
  },
  "amends_treaty": null,
  "chamber": "s",
  "congress": "108",
  "introduced_at": "2004-05-10",
  "number": 3134,
  "proposed_at": "2004-05-11T04:00:00Z",
  "purpose": "To strike the international tax provisions that are unrelated to the FSC/ETI repeal and eliminate the phase-in of the deduction for qualified production activities income.",
  "sponsor": {
    "bioguide_id": "H000725",
    "district": null,
    "name": "Hollings, Ernest F.",
    "state": "SC",
    "title": "Sen.",
    "type": "person"
  },
  "status": "fail",
  "status_at": "2004-05-11",
  "updated_at": "2022-02-03T05:37:18Z"
}