<bill session="119" type="h" number="4426" updated="2025-11-01T08:05:35Z">
  <state datetime="2025-07-16">REFERRED</state>
  <status>
    <introduced datetime="2025-07-16"/>
  </status>
  <introduced datetime="2025-07-16"/>
  <titles>
    <title type="display">SMART Act</title>
    <title type="short" as="introduced">SMART Act</title>
    <title type="short" as="introduced">Studying Mitigation And Reporting Transparently Act</title>
    <title type="official" as="introduced">To direct the Administrator of the Federal Emergency Management Agency to conduct a study to evaluate the effectiveness, long-term cost savings, and strategic impact of Federal Emergency Management Agency-funded hazard mitigation activities across the United States, and for other purposes.</title>
  </titles>
  <sponsor bioguide_id="B001327"/>
  <cosponsors>
    <cosponsor bioguide_id="G000559" joined="2025-07-16"/>
    <cosponsor bioguide_id="G000602" joined="2025-10-31"/>
    <cosponsor bioguide_id="S001211" joined="2025-07-21"/>
    <cosponsor bioguide_id="V000138" joined="2025-10-28"/>
  </cosponsors>
  <actions>
    <action datetime="2025-07-16">
      <text>Introduced in House</text>
    </action>
    <action datetime="2025-07-16" state="REFERRED">
      <text>Referred to the House Committee on Transportation and Infrastructure.</text>
    </action>
    <action datetime="2025-07-17">
      <text>Referred to the Subcommittee on Economic Development, Public Buildings, and Emergency Management.</text>
    </action>
  </actions>
  <committees>
    <committee code="HSPW" name="House Transportation and Infrastructure" subcommittee="" activity="Referred To"/>
    <committee code="HSPW13" name="House Transportation and Infrastructure" subcommittee="Economic Development, Public Buildings, and Emergency Management" activity="Referral"/>
  </committees>
  <relatedbills/>
  <subjects>
    <term name="Emergency management"/>
  </subjects>
  <amendments/>
</bill>
