{
  "actions": [
    {
      "acted_at": "2020-10-19",
      "action_code": "10000",
      "references": [],
      "text": "Introduced in Senate",
      "type": "action"
    },
    {
      "acted_at": "2020-10-19",
      "action_code": "",
      "committees": [
        "SSFI"
      ],
      "references": [],
      "status": "REFERRED",
      "text": "Read twice and referred to the Committee on Finance.",
      "type": "referral"
    }
  ],
  "amendments": [],
  "bill_id": "s4810-116",
  "bill_type": "s",
  "by_request": false,
  "committee_reports": [],
  "committees": [
    {
      "activity": [
        "referral"
      ],
      "committee": "Senate Finance",
      "committee_id": "SSFI"
    }
  ],
  "congress": "116",
  "cosponsors": [
    {
      "bioguide_id": "B001267",
      "district": null,
      "name": "Bennet, Michael F.",
      "original_cosponsor": true,
      "sponsored_at": "2020-10-19",
      "state": "CO",
      "title": "Sen.",
      "withdrawn_at": null
    },
    {
      "bioguide_id": "B001277",
      "district": null,
      "name": "Blumenthal, Richard",
      "original_cosponsor": true,
      "sponsored_at": "2020-10-19",
      "state": "CT",
      "title": "Sen.",
      "withdrawn_at": null
    },
    {
      "bioguide_id": "C000141",
      "district": null,
      "name": "Cardin, Benjamin L.",
      "original_cosponsor": true,
      "sponsored_at": "2020-10-19",
      "state": "MD",
      "title": "Sen.",
      "withdrawn_at": null
    },
    {
      "bioguide_id": "C001035",
      "district": null,
      "name": "Collins, Susan M.",
      "original_cosponsor": true,
      "sponsored_at": "2020-10-19",
      "state": "ME",
      "title": "Sen.",
      "withdrawn_at": null
    },
    {
      "bioguide_id": "D000563",
      "district": null,
      "name": "Durbin, Richard J.",
      "original_cosponsor": true,
      "sponsored_at": "2020-10-19",
      "state": "IL",
      "title": "Sen.",
      "withdrawn_at": null
    },
    {
      "bioguide_id": "F000062",
      "district": null,
      "name": "Feinstein, Dianne",
      "original_cosponsor": true,
      "sponsored_at": "2020-10-19",
      "state": "CA",
      "title": "Sen.",
      "withdrawn_at": null
    },
    {
      "bioguide_id": "H001042",
      "district": null,
      "name": "Hirono, Mazie K.",
      "original_cosponsor": true,
      "sponsored_at": "2020-10-19",
      "state": "HI",
      "title": "Sen.",
      "withdrawn_at": null
    },
    {
      "bioguide_id": "K000384",
      "district": null,
      "name": "Kaine, Tim",
      "original_cosponsor": true,
      "sponsored_at": "2020-10-19",
      "state": "VA",
      "title": "Sen.",
      "withdrawn_at": null
    },
    {
      "bioguide_id": "M001183",
      "district": null,
      "name": "Manchin, Joe, III",
      "original_cosponsor": true,
      "sponsored_at": "2020-10-19",
      "state": "WV",
      "title": "Sen.",
      "withdrawn_at": null
    },
    {
      "bioguide_id": "M000133",
      "district": null,
      "name": "Markey, Edward J.",
      "original_cosponsor": true,
      "sponsored_at": "2020-10-19",
      "state": "MA",
      "title": "Sen.",
      "withdrawn_at": null
    },
    {
      "bioguide_id": "M001111",
      "district": null,
      "name": "Murray, Patty",
      "original_cosponsor": true,
      "sponsored_at": "2020-10-19",
      "state": "WA",
      "title": "Sen.",
      "withdrawn_at": null
    },
    {
      "bioguide_id": "R000122",
      "district": null,
      "name": "Reed, Jack",
      "original_cosponsor": true,
      "sponsored_at": "2020-10-19",
      "state": "RI",
      "title": "Sen.",
      "withdrawn_at": null
    },
    {
      "bioguide_id": "S001191",
      "district": null,
      "name": "Sinema, Kyrsten",
      "original_cosponsor": true,
      "sponsored_at": "2020-10-19",
      "state": "AZ",
      "title": "Sen.",
      "withdrawn_at": null
    },
    {
      "bioguide_id": "W000805",
      "district": null,
      "name": "Warner, Mark R.",
      "original_cosponsor": true,
      "sponsored_at": "2020-10-19",
      "state": "VA",
      "title": "Sen.",
      "withdrawn_at": null
    },
    {
      "bioguide_id": "W000817",
      "district": null,
      "name": "Warren, Elizabeth",
      "original_cosponsor": true,
      "sponsored_at": "2020-10-19",
      "state": "MA",
      "title": "Sen.",
      "withdrawn_at": null
    },
    {
      "bioguide_id": "W000802",
      "district": null,
      "name": "Whitehouse, Sheldon",
      "original_cosponsor": true,
      "sponsored_at": "2020-10-19",
      "state": "RI",
      "title": "Sen.",
      "withdrawn_at": null
    },
    {
      "bioguide_id": "W000779",
      "district": null,
      "name": "Wyden, Ron",
      "original_cosponsor": true,
      "sponsored_at": "2020-10-19",
      "state": "OR",
      "title": "Sen.",
      "withdrawn_at": null
    }
  ],
  "enacted_as": null,
  "history": {
    "active": false,
    "awaiting_signature": false,
    "enacted": false,
    "vetoed": false
  },
  "introduced_at": "2020-10-19",
  "number": "4810",
  "official_title": "A bill to require employee consent for any deferral of payroll taxes.",
  "popular_title": null,
  "related_bills": [
    {
      "bill_id": "hr8629-116",
      "identified_by": "CRS",
      "reason": "identical",
      "type": "bill"
    }
  ],
  "short_title": "Protecting Employees from Surprise Taxes Act of 2020",
  "sponsor": {
    "bioguide_id": "V000128",
    "district": null,
    "name": "Van Hollen, Chris",
    "state": "MD",
    "title": "Sen.",
    "type": "person"
  },
  "status": "REFERRED",
  "status_at": "2020-10-19",
  "subjects": [
    "Employment discrimination and employee rights",
    "Employment taxes",
    "Tax administration and collection, taxpayers",
    "Taxation"
  ],
  "subjects_top_term": "Taxation",
  "summary": {
    "as": "Introduced in Senate",
    "asOf": "2020-10-19",
    "date": "2020-11-19T15:10:12Z",
    "text": "Protecting Employees from Surprise Taxes Act of 2020\n\nThis bill prohibits employers from deferring payment of payroll taxes unless affected employees provide written consent to a deferral. Employers must also provide notice to their employees of the right to provide or withhold written consent and the future tax liability resulting from providing consent to the deferral of such taxes."
  },
  "titles": [
    {
      "as": null,
      "is_for_portion": false,
      "textVersionCode": null,
      "title": "Protecting Employees from Surprise Taxes Act of 2020",
      "type": "display"
    },
    {
      "as": "introduced",
      "is_for_portion": false,
      "textVersionCode": null,
      "title": "Protecting Employees from Surprise Taxes Act of 2020",
      "type": "short"
    },
    {
      "as": "introduced",
      "is_for_portion": false,
      "textVersionCode": null,
      "title": "A bill to require employee consent for any deferral of payroll taxes.",
      "type": "official"
    }
  ],
  "updated_at": "2023-01-11T13:44:24Z",
  "url": "https://www.govinfo.gov/bulkdata/BILLSTATUS/116/s/BILLSTATUS-116s4810.xml"
}