{
  "actions": [
    {
      "acted_at": "2003-06-05",
      "action_code": "10000",
      "references": [],
      "text": "Introduced in Senate",
      "type": "action"
    },
    {
      "acted_at": "2003-06-05",
      "action_code": "B00100",
      "references": [
        {
          "reference": "CR S7488-7489",
          "type": null
        }
      ],
      "text": "Sponsor introductory remarks on measure.",
      "type": "action"
    },
    {
      "acted_at": "2003-06-05",
      "action_code": "",
      "committees": [
        "SSFI"
      ],
      "references": [
        {
          "reference": "CR S7489",
          "type": "text of measure as introduced"
        }
      ],
      "status": "REFERRED",
      "text": "Read twice and referred to the Committee on Finance.",
      "type": "referral"
    }
  ],
  "amendments": [],
  "bill_id": "s1196-108",
  "bill_type": "s",
  "by_request": false,
  "committee_reports": [],
  "committees": [
    {
      "activity": [
        "referral"
      ],
      "committee": "Senate Finance",
      "committee_id": "SSFI"
    }
  ],
  "congress": "108",
  "cosponsors": [
    {
      "bioguide_id": "A000121",
      "district": null,
      "name": "Allen, George",
      "original_cosponsor": false,
      "sponsored_at": "2003-06-12",
      "state": "VA",
      "title": "Sen.",
      "withdrawn_at": null
    },
    {
      "bioguide_id": "B000953",
      "district": null,
      "name": "Brownback, Sam",
      "original_cosponsor": true,
      "sponsored_at": "2003-06-05",
      "state": "KS",
      "title": "Sen.",
      "withdrawn_at": null
    },
    {
      "bioguide_id": "B001066",
      "district": null,
      "name": "Bunning, Jim",
      "original_cosponsor": true,
      "sponsored_at": "2003-06-05",
      "state": "KY",
      "title": "Sen.",
      "withdrawn_at": null
    },
    {
      "bioguide_id": "B001126",
      "district": null,
      "name": "Burns, Conrad R.",
      "original_cosponsor": true,
      "sponsored_at": "2003-06-05",
      "state": "MT",
      "title": "Sen.",
      "withdrawn_at": null
    },
    {
      "bioguide_id": "C000286",
      "district": null,
      "name": "Chambliss, Saxby",
      "original_cosponsor": false,
      "sponsored_at": "2003-06-12",
      "state": "GA",
      "title": "Sen.",
      "withdrawn_at": null
    },
    {
      "bioguide_id": "C000567",
      "district": null,
      "name": "Cochran, Thad",
      "original_cosponsor": true,
      "sponsored_at": "2003-06-05",
      "state": "MS",
      "title": "Sen.",
      "withdrawn_at": null
    },
    {
      "bioguide_id": "C001056",
      "district": null,
      "name": "Cornyn, John",
      "original_cosponsor": false,
      "sponsored_at": "2003-06-12",
      "state": "TX",
      "title": "Sen.",
      "withdrawn_at": null
    },
    {
      "bioguide_id": "E000194",
      "district": null,
      "name": "Ensign, John",
      "original_cosponsor": false,
      "sponsored_at": "2003-06-26",
      "state": "NV",
      "title": "Sen.",
      "withdrawn_at": null
    },
    {
      "bioguide_id": "F000442",
      "district": null,
      "name": "Fitzgerald, Peter",
      "original_cosponsor": true,
      "sponsored_at": "2003-06-05",
      "state": "IL",
      "title": "Sen.",
      "withdrawn_at": null
    },
    {
      "bioguide_id": "H001028",
      "district": null,
      "name": "Hagel, Chuck",
      "original_cosponsor": true,
      "sponsored_at": "2003-06-05",
      "state": "NE",
      "title": "Sen.",
      "withdrawn_at": null
    },
    {
      "bioguide_id": "W000154",
      "district": null,
      "name": "Warner, John",
      "original_cosponsor": false,
      "sponsored_at": "2003-07-08",
      "state": "VA",
      "title": "Sen.",
      "withdrawn_at": null
    }
  ],
  "enacted_as": null,
  "history": {
    "active": false,
    "awaiting_signature": false,
    "enacted": false,
    "vetoed": false
  },
  "introduced_at": "2003-06-05",
  "number": "1196",
  "official_title": "A bill to eliminate the marriage penalty permanently in 2003.",
  "popular_title": null,
  "related_bills": [],
  "short_title": "Permanent Marriage Penalty Relief Act of 2003",
  "sponsor": {
    "bioguide_id": "H001016",
    "district": null,
    "name": "Hutchison, Kay Bailey",
    "state": "TX",
    "title": "Sen.",
    "type": "person"
  },
  "status": "REFERRED",
  "status_at": "2003-06-05",
  "subjects": [
    "Congress",
    "Earned income tax credit",
    "Families",
    "Income tax",
    "Married people",
    "Sunset legislation",
    "Tax deductions",
    "Tax rates",
    "Taxation"
  ],
  "subjects_top_term": "Taxation",
  "summary": {
    "as": "Introduced in Senate",
    "asOf": "2003-06-05",
    "date": "2003-08-27T16:50:14Z",
    "text": "Permanent Marriage Penalty Relief Act of 2003 - Amends the Internal Revenue Code to provide that the basic standard deduction on a joint return shall be equal to 200 percent of the dollar amount of an individual who is not married.\n\nMakes the maximum taxable income in the lowest joint bracket equal to double the maximum taxable income in the lowest single filer bracket.\n\nIncreases the earned income credit phaseout amount on a joint return by $3,000."
  },
  "titles": [
    {
      "as": null,
      "is_for_portion": false,
      "textVersionCode": null,
      "title": "Permanent Marriage Penalty Relief Act of 2003",
      "type": "display"
    },
    {
      "as": "introduced",
      "is_for_portion": false,
      "textVersionCode": null,
      "title": "A bill to eliminate the marriage penalty permanently in 2003.",
      "type": "official"
    },
    {
      "as": "introduced",
      "is_for_portion": false,
      "textVersionCode": null,
      "title": "Permanent Marriage Penalty Relief Act of 2003",
      "type": "short"
    }
  ],
  "updated_at": "2023-01-15T16:48:45Z",
  "url": "https://www.govinfo.gov/bulkdata/BILLSTATUS/108/s/BILLSTATUS-108s1196.xml"
}