{
  "actions": [
    {
      "acted_at": "2010-05-18",
      "action_code": "Intro-H",
      "references": [],
      "text": "Introduced in House",
      "type": "action"
    },
    {
      "acted_at": "2010-05-18",
      "action_code": "H11100",
      "committees": [
        "HSFA"
      ],
      "references": [],
      "status": "REFERRED",
      "text": "Referred to the House Committee on Foreign Affairs.",
      "type": "referral"
    }
  ],
  "amendments": [],
  "bill_id": "hres1367-111",
  "bill_type": "hres",
  "by_request": false,
  "committee_reports": [],
  "committees": [
    {
      "activity": [
        "referral"
      ],
      "committee": "House Foreign Affairs",
      "committee_id": "HSFA"
    }
  ],
  "congress": "111",
  "cosponsors": [
    {
      "bioguide_id": "C000714",
      "district": "14",
      "name": "Conyers, John, Jr.",
      "original_cosponsor": true,
      "sponsored_at": "2010-05-18",
      "state": "MI",
      "title": "Rep.",
      "withdrawn_at": null
    },
    {
      "bioguide_id": "F000116",
      "district": "51",
      "name": "Filner, Bob",
      "original_cosponsor": true,
      "sponsored_at": "2010-05-18",
      "state": "CA",
      "title": "Rep.",
      "withdrawn_at": null
    },
    {
      "bioguide_id": "J000032",
      "district": "18",
      "name": "Jackson Lee, Sheila",
      "original_cosponsor": true,
      "sponsored_at": "2010-05-18",
      "state": "TX",
      "title": "Rep.",
      "withdrawn_at": null
    },
    {
      "bioguide_id": "J000126",
      "district": "30",
      "name": "Johnson, Eddie Bernice",
      "original_cosponsor": true,
      "sponsored_at": "2010-05-18",
      "state": "TX",
      "title": "Rep.",
      "withdrawn_at": null
    },
    {
      "bioguide_id": "J000288",
      "district": "4",
      "name": "Johnson, Henry C. \"Hank,\" Jr.",
      "original_cosponsor": true,
      "sponsored_at": "2010-05-18",
      "state": "GA",
      "title": "Rep.",
      "withdrawn_at": null
    },
    {
      "bioguide_id": "K000180",
      "district": "13",
      "name": "Kilpatrick, Carolyn C.",
      "original_cosponsor": true,
      "sponsored_at": "2010-05-18",
      "state": "MI",
      "title": "Rep.",
      "withdrawn_at": null
    },
    {
      "bioguide_id": "L000551",
      "district": "9",
      "name": "Lee, Barbara",
      "original_cosponsor": true,
      "sponsored_at": "2010-05-18",
      "state": "CA",
      "title": "Rep.",
      "withdrawn_at": null
    },
    {
      "bioguide_id": "M001174",
      "district": "13",
      "name": "McMahon, Michael E.",
      "original_cosponsor": true,
      "sponsored_at": "2010-05-18",
      "state": "NY",
      "title": "Rep.",
      "withdrawn_at": null
    },
    {
      "bioguide_id": "M001148",
      "district": "17",
      "name": "Meek, Kendrick B.",
      "original_cosponsor": true,
      "sponsored_at": "2010-05-18",
      "state": "FL",
      "title": "Rep.",
      "withdrawn_at": null
    },
    {
      "bioguide_id": "P000149",
      "district": "10",
      "name": "Payne, Donald M.",
      "original_cosponsor": true,
      "sponsored_at": "2010-05-18",
      "state": "NJ",
      "title": "Rep.",
      "withdrawn_at": null
    },
    {
      "bioguide_id": "R000053",
      "district": "15",
      "name": "Rangel, Charles B.",
      "original_cosponsor": true,
      "sponsored_at": "2010-05-18",
      "state": "NY",
      "title": "Rep.",
      "withdrawn_at": null
    },
    {
      "bioguide_id": "S000030",
      "district": "47",
      "name": "Sanchez, Loretta",
      "original_cosponsor": true,
      "sponsored_at": "2010-05-18",
      "state": "CA",
      "title": "Rep.",
      "withdrawn_at": null
    },
    {
      "bioguide_id": "W000797",
      "district": "20",
      "name": "Wasserman Schultz, Debbie",
      "original_cosponsor": true,
      "sponsored_at": "2010-05-18",
      "state": "FL",
      "title": "Rep.",
      "withdrawn_at": null
    }
  ],
  "enacted_as": null,
  "history": {
    "active": false,
    "awaiting_signature": false,
    "enacted": false,
    "vetoed": false
  },
  "introduced_at": "2010-05-18",
  "number": "1367",
  "official_title": "Recognizing the significance of the Haitian flag to the people of Haiti and supporting the goals and ideals of Haitian Flag Day.",
  "popular_title": null,
  "related_bills": [],
  "short_title": null,
  "sponsor": {
    "bioguide_id": "C001067",
    "district": "11",
    "name": "Clarke, Yvette D.",
    "state": "NY",
    "title": "Rep.",
    "type": "person"
  },
  "status": "REFERRED",
  "status_at": "2010-05-18",
  "subjects": [
    "Caribbean area",
    "Commemorative events and holidays",
    "Haiti",
    "International affairs",
    "Latin America",
    "National symbols"
  ],
  "subjects_top_term": "International affairs",
  "summary": {
    "as": "Introduced in House",
    "asOf": "2010-05-18",
    "date": "2010-05-19T19:18:13Z",
    "text": "Recognizes the significance of the Haitian flag to the people of Haiti and supports the goals of Haitian Flag Day."
  },
  "titles": [
    {
      "as": null,
      "is_for_portion": false,
      "textVersionCode": null,
      "title": "Recognizing the significance of the Haitian flag to the people of Haiti and supporting the goals and ideals of Haitian Flag Day.",
      "type": "display"
    },
    {
      "as": "introduced",
      "is_for_portion": false,
      "textVersionCode": null,
      "title": "Recognizing the significance of the Haitian flag to the people of Haiti and supporting the goals and ideals of Haitian Flag Day.",
      "type": "official"
    }
  ],
  "updated_at": "2023-01-11T13:20:03Z",
  "url": "https://www.govinfo.gov/bulkdata/BILLSTATUS/111/hres/BILLSTATUS-111hres1367.xml"
}