{
  "actions": [
    {
      "acted_at": "2003-03-04",
      "action_code": "Intro-H",
      "references": [],
      "text": "Introduced in House",
      "type": "action"
    },
    {
      "acted_at": "2003-03-04",
      "action_code": "H11100",
      "committees": [
        "HSPW"
      ],
      "references": [],
      "status": "REFERRED",
      "text": "Referred to the House Committee on Transportation and Infrastructure.",
      "type": "referral"
    },
    {
      "acted_at": "2003-03-05",
      "action_code": "",
      "committees": [
        "HSPW"
      ],
      "references": [],
      "text": "Referred to the Subcommittee on Aviation.",
      "type": "referral"
    }
  ],
  "amendments": [],
  "bill_id": "hr1063-108",
  "bill_type": "hr",
  "by_request": false,
  "committee_reports": [],
  "committees": [
    {
      "activity": [
        "referral"
      ],
      "committee": "House Transportation and Infrastructure",
      "committee_id": "HSPW"
    },
    {
      "activity": [
        "referral"
      ],
      "committee": "House Transportation and Infrastructure",
      "committee_id": "HSPW",
      "subcommittee": "Subcommittee on Aviation",
      "subcommittee_id": "05"
    }
  ],
  "congress": "108",
  "cosponsors": [
    {
      "bioguide_id": "B000755",
      "district": "8",
      "name": "Brady, Kevin",
      "original_cosponsor": false,
      "sponsored_at": "2003-06-18",
      "state": "TX",
      "title": "Rep.",
      "withdrawn_at": null
    },
    {
      "bioguide_id": "C000059",
      "district": "44",
      "name": "Calvert, Ken",
      "original_cosponsor": false,
      "sponsored_at": "2003-03-25",
      "state": "CA",
      "title": "Rep.",
      "withdrawn_at": null
    },
    {
      "bioguide_id": "C000191",
      "district": "7",
      "name": "Carson, Julia",
      "original_cosponsor": false,
      "sponsored_at": "2003-06-18",
      "state": "IN",
      "title": "Rep.",
      "withdrawn_at": null
    },
    {
      "bioguide_id": "C000994",
      "district": "50",
      "name": "Cunningham, Randy (Duke)",
      "original_cosponsor": false,
      "sponsored_at": "2003-03-20",
      "state": "CA",
      "title": "Rep.",
      "withdrawn_at": null
    },
    {
      "bioguide_id": "D000429",
      "district": "4",
      "name": "Doolittle, John T.",
      "original_cosponsor": false,
      "sponsored_at": "2003-05-06",
      "state": "CA",
      "title": "Rep.",
      "withdrawn_at": null
    },
    {
      "bioguide_id": "H000444",
      "district": "5",
      "name": "Hefley, Joel",
      "original_cosponsor": false,
      "sponsored_at": "2003-05-06",
      "state": "CO",
      "title": "Rep.",
      "withdrawn_at": null
    },
    {
      "bioguide_id": "H000807",
      "district": "8",
      "name": "Hostettler, John N.",
      "original_cosponsor": false,
      "sponsored_at": "2003-05-22",
      "state": "IN",
      "title": "Rep.",
      "withdrawn_at": null
    },
    {
      "bioguide_id": "I000056",
      "district": "49",
      "name": "Issa, Darrell E.",
      "original_cosponsor": false,
      "sponsored_at": "2004-02-06",
      "state": "CA",
      "title": "Rep.",
      "withdrawn_at": null
    },
    {
      "bioguide_id": "J000032",
      "district": "18",
      "name": "Jackson-Lee, Sheila",
      "original_cosponsor": false,
      "sponsored_at": "2003-05-15",
      "state": "TX",
      "title": "Rep.",
      "withdrawn_at": null
    },
    {
      "bioguide_id": "J000174",
      "district": "3",
      "name": "Johnson, Sam",
      "original_cosponsor": false,
      "sponsored_at": "2003-03-25",
      "state": "TX",
      "title": "Rep.",
      "withdrawn_at": null
    },
    {
      "bioguide_id": "J000255",
      "district": "3",
      "name": "Jones, Walter B., Jr.",
      "original_cosponsor": false,
      "sponsored_at": "2003-05-22",
      "state": "NC",
      "title": "Rep.",
      "withdrawn_at": null
    },
    {
      "bioguide_id": "L000397",
      "district": "16",
      "name": "Lofgren, Zoe",
      "original_cosponsor": false,
      "sponsored_at": "2003-05-06",
      "state": "CA",
      "title": "Rep.",
      "withdrawn_at": null
    },
    {
      "bioguide_id": "L000558",
      "district": "4",
      "name": "Lucas, Ken",
      "original_cosponsor": false,
      "sponsored_at": "2003-05-09",
      "state": "KY",
      "title": "Rep.",
      "withdrawn_at": null
    },
    {
      "bioguide_id": "M001144",
      "district": "1",
      "name": "Miller, Jeff",
      "original_cosponsor": false,
      "sponsored_at": "2003-06-09",
      "state": "FL",
      "title": "Rep.",
      "withdrawn_at": null
    },
    {
      "bioguide_id": "P000034",
      "district": "6",
      "name": "Pallone, Frank, Jr.",
      "original_cosponsor": false,
      "sponsored_at": "2003-06-04",
      "state": "NJ",
      "title": "Rep.",
      "withdrawn_at": "2003-07-08"
    },
    {
      "bioguide_id": "P000583",
      "district": "14",
      "name": "Paul, Ron",
      "original_cosponsor": false,
      "sponsored_at": "2003-05-07",
      "state": "TX",
      "title": "Rep.",
      "withdrawn_at": null
    },
    {
      "bioguide_id": "P000373",
      "district": "16",
      "name": "Pitts, Joseph R.",
      "original_cosponsor": false,
      "sponsored_at": "2003-06-04",
      "state": "PA",
      "title": "Rep.",
      "withdrawn_at": null
    },
    {
      "bioguide_id": "P000419",
      "district": "11",
      "name": "Pombo, Richard W.",
      "original_cosponsor": false,
      "sponsored_at": "2003-05-09",
      "state": "CA",
      "title": "Rep.",
      "withdrawn_at": null
    },
    {
      "bioguide_id": "S000250",
      "district": "32",
      "name": "Sessions, Pete",
      "original_cosponsor": false,
      "sponsored_at": "2003-05-06",
      "state": "TX",
      "title": "Rep.",
      "withdrawn_at": null
    },
    {
      "bioguide_id": "S001143",
      "district": "3",
      "name": "Souder, Mark E.",
      "original_cosponsor": false,
      "sponsored_at": "2003-03-20",
      "state": "IN",
      "title": "Rep.",
      "withdrawn_at": null
    },
    {
      "bioguide_id": "T000193",
      "district": "2",
      "name": "Thompson, Bennie G.",
      "original_cosponsor": false,
      "sponsored_at": "2003-05-07",
      "state": "MS",
      "title": "Rep.",
      "withdrawn_at": null
    },
    {
      "bioguide_id": "T000238",
      "district": "13",
      "name": "Thornberry, Mac",
      "original_cosponsor": false,
      "sponsored_at": "2003-05-22",
      "state": "TX",
      "title": "Rep.",
      "withdrawn_at": null
    },
    {
      "bioguide_id": "W000119",
      "district": "3",
      "name": "Wamp, Zach",
      "original_cosponsor": false,
      "sponsored_at": "2003-05-07",
      "state": "TN",
      "title": "Rep.",
      "withdrawn_at": null
    },
    {
      "bioguide_id": "W000795",
      "district": "2",
      "name": "Wilson, Joe",
      "original_cosponsor": false,
      "sponsored_at": "2003-06-18",
      "state": "SC",
      "title": "Rep.",
      "withdrawn_at": null
    }
  ],
  "enacted_as": null,
  "history": {
    "active": false,
    "awaiting_signature": false,
    "enacted": false,
    "vetoed": false
  },
  "introduced_at": "2003-03-04",
  "number": "1063",
  "official_title": "To limit the age restrictions imposed by the Administrator of the Federal Aviation Administration for the issuance or renewal of certain airman certificates, and for other purposes.",
  "popular_title": null,
  "related_bills": [
    {
      "bill_id": "s959-108",
      "identified_by": "CRS",
      "reason": "related",
      "type": "bill"
    }
  ],
  "short_title": null,
  "sponsor": {
    "bioguide_id": "G000152",
    "district": "2",
    "name": "Gibbons, Jim",
    "state": "NV",
    "title": "Rep.",
    "type": "person"
  },
  "status": "REFERRED",
  "status_at": "2003-03-04",
  "subjects": [
    "Age discrimination",
    "Aircraft pilots",
    "Airline employees",
    "Airlines",
    "Civil Rights and Liberties, Minority Issues",
    "Commerce",
    "Labor and Employment",
    "Law",
    "Licenses",
    "Retirement age",
    "Social Welfare",
    "Transportation and public works"
  ],
  "subjects_top_term": "Transportation and public works",
  "summary": {
    "as": "Introduced in House",
    "asOf": "2003-03-04",
    "date": "2006-11-28T17:35:40Z",
    "text": "Amends Federal aviation law to prohibit the Administrator of the Federal Aviation Administration, solely by reason of a person's age if 65 years old or younger, from: (1) refusing to issue to, or renew for, such person an airman certificate for the operation of a commercial aircraft; or (2) requiring an air carrier to terminate the employment of, or refuse to employ, such person as a pilot on such aircraft. Applies this prohibition only with respect to persons who have not reached age 60 as of the enactment of this Act."
  },
  "titles": [
    {
      "as": null,
      "is_for_portion": false,
      "textVersionCode": null,
      "title": "To limit the age restrictions imposed by the Administrator of the Federal Aviation Administration for the issuance or renewal of certain airman certificates, and for other purposes.",
      "type": "display"
    },
    {
      "as": "introduced",
      "is_for_portion": false,
      "textVersionCode": null,
      "title": "To limit the age restrictions imposed by the Administrator of the Federal Aviation Administration for the issuance or renewal of certain airman certificates, and for other purposes.",
      "type": "official"
    }
  ],
  "updated_at": "2023-01-15T22:18:37Z",
  "url": "https://www.govinfo.gov/bulkdata/BILLSTATUS/108/hr/BILLSTATUS-108hr1063.xml"
}