{
  "actions": [
    {
      "acted_at": "2003-06-09",
      "action_code": "10000",
      "references": [],
      "text": "Introduced in Senate",
      "type": "action"
    },
    {
      "acted_at": "2003-06-09",
      "action_code": "",
      "committees": [
        "SSCM"
      ],
      "references": [],
      "status": "REFERRED",
      "text": "Read twice and referred to the Committee on Commerce, Science, and Transportation.",
      "type": "referral"
    }
  ],
  "amendments": [],
  "bill_id": "s1216-108",
  "bill_type": "s",
  "by_request": false,
  "committee_reports": [],
  "committees": [
    {
      "activity": [
        "referral"
      ],
      "committee": "Senate Commerce, Science, and Transportation",
      "committee_id": "SSCM"
    }
  ],
  "congress": "108",
  "cosponsors": [
    {
      "bioguide_id": "B000711",
      "district": null,
      "name": "Boxer, Barbara",
      "original_cosponsor": true,
      "sponsored_at": "2003-06-09",
      "state": "CA",
      "title": "Sen.",
      "withdrawn_at": null
    }
  ],
  "enacted_as": null,
  "history": {
    "active": false,
    "awaiting_signature": false,
    "enacted": false,
    "vetoed": false
  },
  "introduced_at": "2003-06-09",
  "number": "1216",
  "official_title": "A bill to improve wireless telephone service, and for other purposes.",
  "popular_title": null,
  "related_bills": [],
  "short_title": "Cell Phone Users Bill of Rights",
  "sponsor": {
    "bioguide_id": "S000148",
    "district": null,
    "name": "Schumer, Charles E.",
    "state": "NY",
    "title": "Sen.",
    "type": "person"
  },
  "status": "REFERRED",
  "status_at": "2003-06-09",
  "subjects": [
    "Administrative procedure",
    "Administrative remedies",
    "Commerce",
    "Common carriers",
    "Consumer complaints",
    "Consumer education",
    "Consumer protection",
    "Federal Communications Commission",
    "Fines (Penalties)",
    "Government Operations and Politics",
    "Government paperwork",
    "Law",
    "Science, technology, communications",
    "Telecommunication industry",
    "Wireless communication"
  ],
  "subjects_top_term": "Science, technology, communications",
  "summary": {
    "as": "Introduced in Senate",
    "asOf": "2003-06-09",
    "date": "2003-09-10T17:40:31Z",
    "text": "Cell Phone Users Bill of Rights - Directs the Federal Communications Commission (FCC) to require each wireless telephone service provider (provider) offering service in one of the largest 100 U.S. metropolitan statistical areas to provide consumers with the option to port (retain) telephone numbers between providers by implementing wireless telephone number portability throughout the networks of providers in each of those statistical areas. Mandates subsequent implementation of such requirement with respect to all other metropolitan statistical areas in which three or more providers provide wireless service.\n\nDirects the FCC to require providers to include specified information in their wireless telephone service plans, including charges, minutes allowed, contract length, start-up fees, and taxes and surcharges.\n\nRequires each provider to make available, including on the Internet, a map of their service area.\n\nDirects the FCC to monitor the quality of wireless service through semiannual provider reports.\n\nEmpowers the FCC to, and the States to bring civil actions in U.S. district court to, enforce provisions of this Act."
  },
  "titles": [
    {
      "as": null,
      "is_for_portion": false,
      "textVersionCode": null,
      "title": "Cell Phone Users Bill of Rights",
      "type": "display"
    },
    {
      "as": "introduced",
      "is_for_portion": false,
      "textVersionCode": null,
      "title": "A bill to improve wireless telephone service, and for other purposes.",
      "type": "official"
    },
    {
      "as": "introduced",
      "is_for_portion": false,
      "textVersionCode": null,
      "title": "Cell Phone Users Bill of Rights",
      "type": "short"
    }
  ],
  "updated_at": "2023-01-15T16:48:44Z",
  "url": "https://www.govinfo.gov/bulkdata/BILLSTATUS/108/s/BILLSTATUS-108s1216.xml"
}