<bill session="116" type="h" number="4790" updated="2022-11-01T04:17:47Z">
  <state datetime="2019-10-22">REFERRED</state>
  <status>
    <introduced datetime="2019-10-22"/>
  </status>
  <introduced datetime="2019-10-22"/>
  <titles>
    <title type="display">Neil A. Armstrong Test Facility Act</title>
    <title type="official" as="introduced">To redesignate the NASA John H. Glenn Research Center at Plum Brook Station, Ohio, as the NASA John H. Glenn Research Center at the Neil A. Armstrong Test Facility.</title>
    <title type="short" as="introduced">Neil A. Armstrong Test Facility Act</title>
  </titles>
  <sponsor bioguide_id="K000009"/>
  <cosponsors>
    <cosponsor bioguide_id="B001306" joined="2019-10-22"/>
    <cosponsor bioguide_id="B001281" joined="2019-10-22"/>
    <cosponsor bioguide_id="C000266" joined="2019-10-22"/>
    <cosponsor bioguide_id="D000626" joined="2019-10-22"/>
    <cosponsor bioguide_id="F000455" joined="2019-10-22"/>
    <cosponsor bioguide_id="G000563" joined="2019-10-22"/>
    <cosponsor bioguide_id="G000588" joined="2019-10-22"/>
    <cosponsor bioguide_id="H001083" joined="2019-10-31"/>
    <cosponsor bioguide_id="J000292" joined="2019-10-22"/>
    <cosponsor bioguide_id="J000289" joined="2019-10-22"/>
    <cosponsor bioguide_id="J000295" joined="2019-10-22"/>
    <cosponsor bioguide_id="L000566" joined="2019-10-22"/>
    <cosponsor bioguide_id="P000599" joined="2019-10-22"/>
    <cosponsor bioguide_id="R000577" joined="2019-10-22"/>
    <cosponsor bioguide_id="S001187" joined="2019-10-22"/>
    <cosponsor bioguide_id="T000463" joined="2019-10-22"/>
    <cosponsor bioguide_id="W000815" joined="2019-10-22"/>
  </cosponsors>
  <actions>
    <action datetime="2019-10-22">
      <text>Introduced in House</text>
    </action>
    <action datetime="2019-10-22">
      <text>Sponsor introductory remarks on measure.</text>
      <reference ref="CR E1327"/>
    </action>
    <action datetime="2019-10-22" state="REFERRED">
      <text>Referred to the Subcommittee on Space and Aeronautics.</text>
    </action>
    <action datetime="2019-10-22">
      <text>Referred to the House Committee on Science, Space, and Technology.</text>
    </action>
  </actions>
  <committees>
    <committee code="HSSY" name="House Science, Space, and Technology" subcommittee="" activity="Referral"/>
    <committee code="HSSY16" name="House Science, Space, and Technology" subcommittee="Space and Aeronautics" activity="Referral"/>
  </committees>
  <relatedbills>
    <bill session="116" type="s" number="2472" relation="identical"/>
  </relatedbills>
  <subjects>
    <term name="Science, technology, communications"/>
    <term name="Congressional tributes"/>
    <term name="Government buildings, facilities, and property"/>
    <term name="National Aeronautics and Space Administration"/>
    <term name="Ohio"/>
    <term name="Space flight and exploration"/>
    <term name="Spacecraft and satellites"/>
    <term name="U.S. history"/>
  </subjects>
  <amendments/>
  <summary date="2019-11-06T20:03:04Z" status="Introduced in House">Neil A. Armstrong Test Facility Act

This bill redesignates the NASA John H. Glenn Research Center at Plum Brook Station in Ohio as the "NASA John H. Glenn Research Center at the Neil A. Armstrong Test Facility."</summary>
</bill>
