{
  "actions": [
    {
      "acted_at": "2021-06-21",
      "action_code": "10000",
      "references": [],
      "text": "Introduced in Senate",
      "type": "action"
    },
    {
      "acted_at": "2021-06-21",
      "action_code": "",
      "committees": [
        "SSJU"
      ],
      "references": [],
      "status": "REFERRED",
      "text": "Read twice and referred to the Committee on the Judiciary.",
      "type": "referral"
    }
  ],
  "amendments": [],
  "bill_id": "s2141-117",
  "bill_type": "s",
  "by_request": false,
  "committee_reports": [],
  "committees": [
    {
      "activity": [
        "referral"
      ],
      "committee": "Senate Judiciary",
      "committee_id": "SSJU"
    }
  ],
  "congress": "117",
  "cosponsors": [],
  "enacted_as": null,
  "history": {
    "active": false,
    "awaiting_signature": false,
    "enacted": false,
    "vetoed": false
  },
  "introduced_at": "2021-06-21",
  "number": "2141",
  "official_title": "A bill to amend title 18, United States Code, to provide an additional tool to prevent certain frauds against veterans, and for other purposes.",
  "popular_title": null,
  "related_bills": [],
  "short_title": "Preventing Crimes Against Veterans Act of 2021",
  "sponsor": {
    "bioguide_id": "R000595",
    "district": null,
    "name": "Rubio, Marco",
    "state": "FL",
    "title": "Sen.",
    "type": "person"
  },
  "status": "REFERRED",
  "status_at": "2021-06-21",
  "subjects": [
    "Crime and law enforcement",
    "Fraud offenses and financial crimes",
    "Military personnel and dependents",
    "Veterans' pensions and compensation"
  ],
  "subjects_top_term": "Crime and law enforcement",
  "summary": {
    "as": "Introduced in Senate",
    "asOf": "2021-06-21",
    "date": "2021-08-26T15:11:17Z",
    "text": "Preventing Crimes Against Veterans Act of 2021\n\nThis bill establishes a new criminal offense for knowingly engaging in any scheme to defraud an individual of veterans' benefits, or in connection with obtaining veteran's benefits for an individual. A violator is subject to criminal penalties\u2014a fine, a prison term of up to five years, or both."
  },
  "titles": [
    {
      "as": "introduced",
      "is_for_portion": false,
      "textVersionCode": null,
      "title": "A bill to amend title 18, United States Code, to provide an additional tool to prevent certain frauds against veterans, and for other purposes.",
      "type": "official"
    },
    {
      "as": null,
      "is_for_portion": false,
      "textVersionCode": null,
      "title": "Preventing Crimes Against Veterans Act of 2021",
      "type": "display"
    },
    {
      "as": "introduced",
      "is_for_portion": false,
      "textVersionCode": null,
      "title": "Preventing Crimes Against Veterans Act of 2021",
      "type": "short"
    }
  ],
  "updated_at": "2022-12-31T05:26:49Z",
  "url": "https://www.govinfo.gov/bulkdata/BILLSTATUS/117/s/BILLSTATUS-117s2141.xml"
}